pytest_shared_session_scope/__init__.py
pytest_shared_session_scope/_scheduler.py
pytest_shared_session_scope/_types.py
pytest_shared_session_scope/fixtures.py
pytest_shared_session_scope/plugin.py
pytest_shared_session_scope/store.py
pytest_shared_session_scope/types.py
pytest_shared_session_scope-0.5.1.dist-info/METADATA
pytest_shared_session_scope-0.5.1.dist-info/WHEEL
pytest_shared_session_scope-0.5.1.dist-info/entry_points.txt
pytest_shared_session_scope-0.5.1.dist-info/licenses/LICENSE
pytest_shared_session_scope-0.5.1.dist-info/RECORD
