Metadata-Version: 2.4
Name: pytest-shared-session-scope
Version: 0.5.1
Summary: Pytest session-scoped fixture that works with xdist
Author-email: Stefan Rasmussen <opensource@bruhn.io>
License-File: LICENSE
Requires-Python: >=3.10
Requires-Dist: filelock>=3.16.0
Requires-Dist: pytest>=7.0.0
Requires-Dist: typing-extensions>=3.6.2
